{"runner": {"num_initial_experiments": null, "max_iterations": 20, "batch_size": 1, "f_tol": 1e-05, "max_restarts": 0}, "strategy": {"name": "MTBO", "transform": {"transform_domain": [{"type": "CategoricalVariable", "is_objective": false, "maximize": true, "name": "inputs[\"Catalyst\"].components[0].identifiers[0].value", "description": "Catalyst", "units": null, "levels": ["cycloPd tBuXPhos 4-Chlorotoluene", "cycloPd EPhos 4-Chlorotoluene", "cycloPd AlPhos 4-Chlorotoluene", "cycloPd tBuBrettPhos 4-Chlorotoluene"], "ds": null}, {"type": "CategoricalVariable", "is_objective": false, "maximize": true, "name": "inputs[\"Base\"].components[0].identifiers[0].value", "description": "Base", "units": null, "levels": ["TEA", "Triethylamine", "TMG", "BTMG", "DBU", "MTBD", "BTTP", "P2Et"], "ds": null}, {"type": "CategoricalVariable", "is_objective": false, "maximize": true, "name": "inputs[\"Solvent\"].components[0].identifiers[0].value", "description": "Solvent", "units": null, "levels": ["2-MeTHF", "DMSO"], "ds": null}, {"type": "ContinuousVariable", "is_objective": false, "maximize": true, "name": "outcomes[0].reaction_time.value", "description": "Residence time in seconds (s)", "units": null, "bounds": [60.0, 6000.0]}, {"type": "ContinuousVariable", "is_objective": false, "maximize": true, "name": "conditions.temperature.setpoint.value", "description": "Reactor temperature in degrees Celsius (\u00baC)", "units": null, "bounds": [30.0, 110.0]}, {"type": "ContinuousVariable", "is_objective": true, "maximize": true, "name": "outcomes[0].products[0].measurements[0].percentage.value", "description": "Yield", "units": null, "bounds": [0.0, 105.0]}], "name": "Transform", "domain": [{"type": "CategoricalVariable", "is_objective": false, "maximize": true, "name": "inputs[\"Catalyst\"].components[0].identifiers[0].value", "description": "Catalyst", "units": null, "levels": ["cycloPd tBuXPhos 4-Chlorotoluene", "cycloPd EPhos 4-Chlorotoluene", "cycloPd AlPhos 4-Chlorotoluene", "cycloPd tBuBrettPhos 4-Chlorotoluene"], "ds": null}, {"type": "CategoricalVariable", "is_objective": false, "maximize": true, "name": "inputs[\"Base\"].components[0].identifiers[0].value", "description": "Base", "units": null, "levels": ["TEA", "Triethylamine", "TMG", "BTMG", "DBU", "MTBD", "BTTP", "P2Et"], "ds": null}, {"type": "CategoricalVariable", "is_objective": false, "maximize": true, "name": "inputs[\"Solvent\"].components[0].identifiers[0].value", "description": "Solvent", "units": null, "levels": ["2-MeTHF", "DMSO"], "ds": null}, {"type": "ContinuousVariable", "is_objective": false, "maximize": true, "name": "outcomes[0].reaction_time.value", "description": "Residence time in seconds (s)", "units": null, "bounds": [60.0, 6000.0]}, {"type": "ContinuousVariable", "is_objective": false, "maximize": true, "name": "conditions.temperature.setpoint.value", "description": "Reactor temperature in degrees Celsius (\u00baC)", "units": null, "bounds": [30.0, 110.0]}, {"type": "ContinuousVariable", "is_objective": true, "maximize": true, "name": "outcomes[0].products[0].measurements[0].percentage.value", "description": "Yield", "units": null, "bounds": [0.0, 105.0]}], "transform_params": {}}, "strategy_params": {"all_experiments": {"index": [0, 1, 0, 0, 0, 0, 0, 0, 0, 0, 0, 0, 0, 0, 0, 0, 0, 0, 0, 0], "columns": [["inputs[\"Catalyst\"].components[0].identifiers[0].value", "DATA"], ["inputs[\"Base\"].components[0].identifiers[0].value", "DATA"], ["inputs[\"Solvent\"].components[0].identifiers[0].value", "DATA"], ["outcomes[0].reaction_time.value", "DATA"], ["conditions.temperature.setpoint.value", "DATA"], ["outcomes[0].products[0].measurements[0].percentage.value", "DATA"], ["computation_t", "METADATA"], ["experiment_t", "METADATA"], ["strategy", "METADATA"], ["task", "METADATA"]], "data": [["cycloPd EPhos 4-Chlorotoluene", "TMG", "DMSO", 1545.0, 50.0, 50.08913040161133, 0.0, 0.012979984283447266, "LHS", 1], ["cycloPd EPhos 4-Chlorotoluene", "Triethylamine", "DMSO", 4515.0, 90.0, 96.56049346923828, 0.0, 0.010525941848754883, "LHS", 1], ["cycloPd tBuXPhos 4-Chlorotoluene", "TEA", "2-MeTHF", 168.7243493925164, 49.438399620118936, 0.0, 2.0112807750701904, 0.011146068572998047, "MTBO", 1], ["cycloPd tBuBrettPhos 4-Chlorotoluene", "BTMG", "2-MeTHF", 552.536774023512, 93.42612049333152, 101.85160064697266, 6.654437065124512, 0.010854005813598633, "MTBO", 1], ["cycloPd EPhos 4-Chlorotoluene", "BTMG", "2-MeTHF", 746.8437542269461, 83.9472298607792, 97.58233642578125, 0.5392739772796631, 0.011102914810180664, "MTBO", 1], ["cycloPd tBuBrettPhos 4-Chlorotoluene", "BTMG", "2-MeTHF", 993.4712088831668, 67.76695305690723, 93.25364685058594, 3.1530890464782715, 0.01119685173034668, "MTBO", 1], ["cycloPd AlPhos 4-Chlorotoluene", "BTMG", "2-MeTHF", 933.2829007159871, 65.77969546472433, 95.96794128417969, 2.400369882583618, 0.010996818542480469, "MTBO", 1], ["cycloPd tBuXPhos 4-Chlorotoluene", "DBU", "2-MeTHF", 831.2041384010632, 82.91558510630644, 83.5365982055664, 2.1474359035491943, 0.010782003402709961, "MTBO", 1], ["cycloPd tBuBrettPhos 4-Chlorotoluene", "DBU", "2-MeTHF", 866.1605582716431, 97.71704821458823, 99.74749755859375, 2.2537007331848145, 0.011223793029785156, "MTBO", 1], ["cycloPd AlPhos 4-Chlorotoluene", "BTMG", "2-MeTHF", 1396.047911477407, 55.22370456836766, 96.25507354736328, 2.699702024459839, 0.0108489990234375, "MTBO", 1], ["cycloPd AlPhos 4-Chlorotoluene", "BTMG", "2-MeTHF", 1040.5197188329366, 32.04167716090662, 91.92716217041016, 3.3203351497650146, 0.011080026626586914, "MTBO", 1], ["cycloPd AlPhos 4-Chlorotoluene", "DBU", "2-MeTHF", 1062.1157602510998, 106.38523690697204, 105.0, 2.6933469772338867, 0.010816097259521484, "MTBO", 1], ["cycloPd tBuBrettPhos 4-Chlorotoluene", "DBU", "2-MeTHF", 1272.0763273764526, 110.0, 105.0, 1.9459800720214844, 0.010968685150146484, "MTBO", 1], ["cycloPd tBuBrettPhos 4-Chlorotoluene", "BTMG", "2-MeTHF", 876.6688902856804, 110.0, 104.7794189453125, 1.1896140575408936, 0.010912895202636719, "MTBO", 1], ["cycloPd tBuBrettPhos 4-Chlorotoluene", "DBU", "2-MeTHF", 1316.2659511696454, 87.73159304224696, 92.2496109008789, 2.2102389335632324, 0.010896921157836914, "MTBO", 1], ["cycloPd AlPhos 4-Chlorotoluene", "DBU", "2-MeTHF", 878.3713763416031, 110.0, 105.0, 2.2846100330352783, 0.011001110076904297, "MTBO", 1], ["cycloPd AlPhos 4-Chlorotoluene", "DBU", "2-MeTHF", 1347.3795189769912, 110.0, 105.0, 2.808716058731079, 0.010966062545776367, "MTBO", 1], ["cycloPd EPhos 4-Chlorotoluene", "BTMG", "2-MeTHF", 409.98418150863984, 110.0, 102.8481216430664, 1.3968019485473633, 0.010903120040893555, "MTBO", 1], ["cycloPd AlPhos 4-Chlorotoluene", "DBU", "2-MeTHF", 1144.1565722808427, 110.0, 105.0, 4.57100510597229, 0.010926961898803711, "MTBO", 1], ["cycloPd EPhos 4-Chlorotoluene", "BTMG", "2-MeTHF", 250.6141587893096, 84.15709576655814, 91.71733093261719, 2.2136878967285156, 0.01154184341430664, "MTBO", 1]]}, "categorical_method": "one-hot", "task": 1}}, "experiment": {"domain": [{"type": "CategoricalVariable", "is_objective": false, "maximize": true, "name": "inputs[\"Catalyst\"].components[0].identifiers[0].value", "description": "Catalyst", "units": null, "levels": ["cycloPd tBuXPhos 4-Chlorotoluene", "cycloPd EPhos 4-Chlorotoluene", "cycloPd AlPhos 4-Chlorotoluene", "cycloPd tBuBrettPhos 4-Chlorotoluene"], "ds": null}, {"type": "CategoricalVariable", "is_objective": false, "maximize": true, "name": "inputs[\"Base\"].components[0].identifiers[0].value", "description": "Base", "units": null, "levels": ["TEA", "Triethylamine", "TMG", "BTMG", "DBU", "MTBD", "BTTP", "P2Et"], "ds": null}, {"type": "CategoricalVariable", "is_objective": false, "maximize": true, "name": "inputs[\"Solvent\"].components[0].identifiers[0].value", "description": "Solvent", "units": null, "levels": ["2-MeTHF", "DMSO"], "ds": null}, {"type": "ContinuousVariable", "is_objective": false, "maximize": true, "name": "outcomes[0].reaction_time.value", "description": "Residence time in seconds (s)", "units": null, "bounds": [60.0, 6000.0]}, {"type": "ContinuousVariable", "is_objective": false, "maximize": true, "name": "conditions.temperature.setpoint.value", "description": "Reactor temperature in degrees Celsius (\u00baC)", "units": null, "bounds": [30.0, 110.0]}, {"type": "ContinuousVariable", "is_objective": true, "maximize": true, "name": "outcomes[0].products[0].measurements[0].percentage.value", "description": "Yield", "units": null, "bounds": [0.0, 105.0]}], "name": "ExperimentalEmulator", "data": {"index": [0, 1, 2, 3, 4, 5, 6, 7, 8, 9, 10, 11, 12, 13, 14, 15, 16, 17, 18, 19, 20], "columns": [["inputs[\"Catalyst\"].components[0].identifiers[0].value", "DATA"], ["inputs[\"Base\"].components[0].identifiers[0].value", "DATA"], ["inputs[\"Solvent\"].components[0].identifiers[0].value", "DATA"], ["outcomes[0].reaction_time.value", "DATA"], ["conditions.temperature.setpoint.value", "DATA"], ["outcomes[0].products[0].measurements[0].percentage.value", "DATA"], ["computation_t", "METADATA"], ["experiment_t", "METADATA"], ["strategy", "METADATA"], ["task", "METADATA"]], "data": [["cycloPd EPhos 4-Chlorotoluene", "TMG", "DMSO", 1545.0, 50.0, 50.08913040161133, 0.0, 0.012979984283447266, "LHS", 1], ["cycloPd EPhos 4-Chlorotoluene", "Triethylamine", "DMSO", 4515.0, 90.0, 96.56049346923828, 0.0, 0.010525941848754883, "LHS", 1], ["cycloPd tBuXPhos 4-Chlorotoluene", "TEA", "2-MeTHF", 168.7243493925164, 49.438399620118936, 0.0, 2.0112807750701904, 0.011146068572998047, "MTBO", 1], ["cycloPd tBuBrettPhos 4-Chlorotoluene", "BTMG", "2-MeTHF", 552.536774023512, 93.42612049333152, 101.85160064697266, 6.654437065124512, 0.010854005813598633, "MTBO", 1], ["cycloPd EPhos 4-Chlorotoluene", "BTMG", "2-MeTHF", 746.8437542269461, 83.9472298607792, 97.58233642578125, 0.5392739772796631, 0.011102914810180664, "MTBO", 1], ["cycloPd tBuBrettPhos 4-Chlorotoluene", "BTMG", "2-MeTHF", 993.4712088831668, 67.76695305690723, 93.25364685058594, 3.1530890464782715, 0.01119685173034668, "MTBO", 1], ["cycloPd AlPhos 4-Chlorotoluene", "BTMG", "2-MeTHF", 933.2829007159871, 65.77969546472433, 95.96794128417969, 2.400369882583618, 0.010996818542480469, "MTBO", 1], ["cycloPd tBuXPhos 4-Chlorotoluene", "DBU", "2-MeTHF", 831.2041384010632, 82.91558510630644, 83.5365982055664, 2.1474359035491943, 0.010782003402709961, "MTBO", 1], ["cycloPd tBuBrettPhos 4-Chlorotoluene", "DBU", "2-MeTHF", 866.1605582716431, 97.71704821458823, 99.74749755859375, 2.2537007331848145, 0.011223793029785156, "MTBO", 1], ["cycloPd AlPhos 4-Chlorotoluene", "BTMG", "2-MeTHF", 1396.047911477407, 55.22370456836766, 96.25507354736328, 2.699702024459839, 0.0108489990234375, "MTBO", 1], ["cycloPd AlPhos 4-Chlorotoluene", "BTMG", "2-MeTHF", 1040.5197188329366, 32.04167716090662, 91.92716217041016, 3.3203351497650146, 0.011080026626586914, "MTBO", 1], ["cycloPd AlPhos 4-Chlorotoluene", "DBU", "2-MeTHF", 1062.1157602510998, 106.38523690697204, 105.0, 2.6933469772338867, 0.010816097259521484, "MTBO", 1], ["cycloPd tBuBrettPhos 4-Chlorotoluene", "DBU", "2-MeTHF", 1272.0763273764526, 110.0, 105.0, 1.9459800720214844, 0.010968685150146484, "MTBO", 1], ["cycloPd tBuBrettPhos 4-Chlorotoluene", "BTMG", "2-MeTHF", 876.6688902856804, 110.0, 104.7794189453125, 1.1896140575408936, 0.010912895202636719, "MTBO", 1], ["cycloPd tBuBrettPhos 4-Chlorotoluene", "DBU", "2-MeTHF", 1316.2659511696454, 87.73159304224696, 92.2496109008789, 2.2102389335632324, 0.010896921157836914, "MTBO", 1], ["cycloPd AlPhos 4-Chlorotoluene", "DBU", "2-MeTHF", 878.3713763416031, 110.0, 105.0, 2.2846100330352783, 0.011001110076904297, "MTBO", 1], ["cycloPd AlPhos 4-Chlorotoluene", "DBU", "2-MeTHF", 1347.3795189769912, 110.0, 105.0, 2.808716058731079, 0.010966062545776367, "MTBO", 1], ["cycloPd EPhos 4-Chlorotoluene", "BTMG", "2-MeTHF", 409.98418150863984, 110.0, 102.8481216430664, 1.3968019485473633, 0.010903120040893555, "MTBO", 1], ["cycloPd AlPhos 4-Chlorotoluene", "DBU", "2-MeTHF", 1144.1565722808427, 110.0, 105.0, 4.57100510597229, 0.010926961898803711, "MTBO", 1], ["cycloPd EPhos 4-Chlorotoluene", "BTMG", "2-MeTHF", 250.6141587893096, 84.15709576655814, 91.71733093261719, 2.2136878967285156, 0.01154184341430664, "MTBO", 1], ["cycloPd tBuBrettPhos 4-Chlorotoluene", "DBU", "2-MeTHF", 1678.9787460178227, 110.0, 104.4361343383789, 1.9262151718139648, 0.010973215103149414, "MTBO", 1]]}, "experiment_params": {"model_name": "morpholine_bm", "regressor_name": "ANNRegressor", "n_features": 16, "n_examples": 96, "descriptors_features": [], "output_variable_names": ["outcomes[0].products[0].measurements[0].percentage.value"], "predictors": [{"input_preprocessor": {"num": {"mean_": [687.3238450218649, 72.1764705321368], "var_": [250025.97212166886, 875.5853299983728], "scale_": [500.0259714471528, 29.590291144197497], "n_samples_seen_": 68}}, "output_preprocessor": {"mean_": [54.148393235662404], "var_": [1829.9411815203764], "scale_": [42.777811789762886], "n_samples_seen_": 68}}, {"input_preprocessor": {"num": {"mean_": [704.6011014192001, 72.71884050231048], "var_": [256007.24352800215, 846.1192119954623], "scale_": [505.9715837159258, 29.088128368725656], "n_samples_seen_": 69}}, "output_preprocessor": {"mean_": [56.52591260706169], "var_": [1795.9933321363649], "scale_": [42.37916153177603], "n_samples_seen_": 69}}, {"input_preprocessor": {"num": {"mean_": [728.0559522103572, 75.39710141610408], "var_": [257389.24976843892, 836.5678187577062], "scale_": [507.33544107270774, 28.923482134032653], "n_samples_seen_": 69}}, "output_preprocessor": {"mean_": [58.76172453251438], "var_": [1800.0704497413517], "scale_": [42.42723712123324], "n_samples_seen_": 69}}, {"input_preprocessor": {"num": {"mean_": [728.2893992990687, 75.25507238636847], "var_": [238265.3159362173, 853.7940706111315], "scale_": [488.12428328881293, 29.219754800667502], "n_samples_seen_": 69}}, "output_preprocessor": {"mean_": [63.459437604399696], "var_": [1689.2987720484691], "scale_": [41.101079937739705], "n_samples_seen_": 69}}, {"input_preprocessor": {"num": {"mean_": [699.3141493866409, 75.9971013829328], "var_": [244101.92226928603, 876.1156454835702], "scale_": [494.0667184392064, 29.59925075882108], "n_samples_seen_": 69}}, "output_preprocessor": {"mean_": [64.7905063741449], "var_": [1735.472257529254], "scale_": [41.658999718299214], "n_samples_seen_": 69}}], "clip": true}, "extras": [{}, {}, {}, {}, {}, {}, {}, {}, {}, {}, {}, {}, {}, {}, {}, {}, {}, {}, {}, {}, {}, {}, {}, {}, {}, {}, {}, {}, {}, {}, {}, {}, {}, {}, {}, {}, {}, {}, {}, {}, {}, {}]}}