{"runner": {"num_initial_experiments": null, "max_iterations": 20, "batch_size": 1, "f_tol": 1e-05, "max_restarts": 0}, "strategy": {"name": "MTBO", "transform": {"transform_domain": [{"type": "ContinuousVariable", "is_objective": false, "maximize": true, "name": "conc_cat", "description": "catalyst concentration", "units": null, "bounds": [0.000835, 0.004175]}, {"type": "ContinuousVariable", "is_objective": false, "maximize": true, "name": "t", "description": "reaction time", "units": null, "bounds": [60.0, 600.0]}, {"type": "CategoricalVariable", "is_objective": false, "maximize": true, "name": "cat_index", "description": "Choice of catalyst", "units": null, "levels": [0, 1, 2, 3, 4, 5, 6, 7], "ds": null}, {"type": "ContinuousVariable", "is_objective": false, "maximize": true, "name": "temperature", "description": "Reactor temperature in degress celsius", "units": null, "bounds": [30.0, 110.0]}, {"type": "ContinuousVariable", "is_objective": true, "maximize": true, "name": "y", "description": "yield (%)", "units": null, "bounds": [0.0, 100.0]}], "name": "Transform", "domain": [{"type": "ContinuousVariable", "is_objective": false, "maximize": true, "name": "conc_cat", "description": "catalyst concentration", "units": null, "bounds": [0.000835, 0.004175]}, {"type": "ContinuousVariable", "is_objective": false, "maximize": true, "name": "t", "description": "reaction time", "units": null, "bounds": [60.0, 600.0]}, {"type": "CategoricalVariable", "is_objective": false, "maximize": true, "name": "cat_index", "description": "Choice of catalyst", "units": null, "levels": [0, 1, 2, 3, 4, 5, 6, 7], "ds": null}, {"type": "ContinuousVariable", "is_objective": false, "maximize": true, "name": "temperature", "description": "Reactor temperature in degress celsius", "units": null, "bounds": [30.0, 110.0]}, {"type": "ContinuousVariable", "is_objective": true, "maximize": true, "name": "y", "description": "yield (%)", "units": null, "bounds": [0.0, 100.0]}], "transform_params": {}}, "strategy_params": {"all_experiments": {"index": [0, 1, 0, 0, 0, 0, 0, 0, 0, 0, 0, 0, 0, 0, 0, 0, 0, 0, 0, 0], "columns": [["conc_cat", "DATA"], ["t", "DATA"], ["cat_index", "DATA"], ["temperature", "DATA"], ["y", "DATA"], ["computation_t", "METADATA"], ["experiment_t", "METADATA"], ["strategy", "METADATA"], ["task", "METADATA"]], "data": [[0.00334, 465.0, 4.0, 90.0, 0.750246260608174, 0.0, 0.0022428035736083984, "LHS", 1], [0.00167, 195.0, 2.0, 50.0, 0.06805777203816393, 0.0, 0.0015358924865722656, "LHS", 1], [0.003957641640289146, 415.08639917659383, 4, 97.40190793637804, 0.826311971760352, 1.4956939220428467, 0.0021538734436035156, "MTBO", 1], [0.003669615578608733, 438.42981186220743, 4, 93.97917807908662, 0.8007394776306475, 4.4635009765625, 0.001756906509399414, "MTBO", 1], [0.0038951162814164246, 400.8807175559404, 4, 92.12520601336718, 0.7525278112987781, 3.4772298336029053, 0.0017390251159667969, "MTBO", 1], [0.00407871401883316, 451.90876113431955, 4, 95.2285148377906, 0.8396090200299418, 4.237397909164429, 0.0018177032470703125, "MTBO", 1], [0.003926340147533956, 462.2968554641726, 4, 100.67900240693412, 0.8800760745047087, 5.488891124725342, 0.0017781257629394531, "MTBO", 1], [0.0037341992091332573, 510.13596991635984, 4, 98.18811208803885, 0.8714660830926114, 3.0637240409851074, 0.002151966094970703, "MTBO", 1], [0.004087136035930185, 517.6149699613849, 4, 101.44659847165731, 0.9159796364317272, 2.261536121368408, 0.0021822452545166016, "MTBO", 1], [0.003964688441103026, 536.3002381234614, 4, 108.20204429347446, 0.9452228287621098, 4.869693994522095, 0.0018727779388427734, "MTBO", 1], [0.004175, 510.4096267264086, 4, 110.0, 0.9683337552468166, 2.351754903793335, 0.0018661022186279297, "MTBO", 1], [0.004175, 566.6527729097188, 4, 110.0, 0.9855811721964686, 2.9615418910980225, 0.0024399757385253906, "MTBO", 1], [0.004102427671721276, 548.0860271549869, 5, 110.0, 0.9037251310920013, 2.2423250675201416, 0.0018610954284667969, "MTBO", 1], [0.004027724476170394, 434.9504197235024, 5, 110.0, 0.8688382302254034, 3.2526371479034424, 0.002104043960571289, "MTBO", 1], [0.004087220271854285, 510.915840387994, 5, 96.30989638534083, 0.7807504519615314, 2.7654201984405518, 0.0016808509826660156, "MTBO", 1], [0.004175, 600.0, 4, 110.0, 0.9699694255629838, 2.2179200649261475, 0.0022878646850585938, "MTBO", 1], [0.002887211445917225, 600.0, 4, 110.0, 0.9575388053698998, 1.9559807777404785, 0.0025107860565185547, "MTBO", 1], [0.0027367677146220033, 501.4827312017057, 4, 110.0, 0.9383645017508252, 2.125805139541626, 0.0018658638000488281, "MTBO", 1], [0.002209874263245971, 593.6946367915926, 4, 110.0, 0.9300728468495605, 2.7322838306427, 0.0024709701538085938, "MTBO", 1], [0.002574629995386873, 576.1252291419544, 4, 102.67221407168523, 0.9004038449640558, 4.817676067352295, 0.001847982406616211, "MTBO", 1]]}, "categorical_method": "one-hot", "task": 1}}, "experiment": {"domain": [{"type": "ContinuousVariable", "is_objective": false, "maximize": true, "name": "conc_cat", "description": "catalyst concentration", "units": null, "bounds": [0.000835, 0.004175]}, {"type": "ContinuousVariable", "is_objective": false, "maximize": true, "name": "t", "description": "reaction time", "units": null, "bounds": [60.0, 600.0]}, {"type": "CategoricalVariable", "is_objective": false, "maximize": true, "name": "cat_index", "description": "Choice of catalyst", "units": null, "levels": [0, 1, 2, 3, 4, 5, 6, 7], "ds": null}, {"type": "ContinuousVariable", "is_objective": false, "maximize": true, "name": "temperature", "description": "Reactor temperature in degress celsius", "units": null, "bounds": [30.0, 110.0]}, {"type": "ContinuousVariable", "is_objective": true, "maximize": true, "name": "y", "description": "yield (%)", "units": null, "bounds": [0.0, 100.0]}], "name": "MIT_case2", "data": {"index": [0, 1, 2, 3, 4, 5, 6, 7, 8, 9, 10, 11, 12, 13, 14, 15, 16, 17, 18, 19, 20], "columns": [["conc_cat", "DATA"], ["t", "DATA"], ["cat_index", "DATA"], ["temperature", "DATA"], ["y", "DATA"], ["computation_t", "METADATA"], ["experiment_t", "METADATA"], ["strategy", "METADATA"], ["task", "METADATA"]], "data": [[0.00334, 465.0, 4.0, 90.0, 0.750246260608174, 0.0, 0.0022428035736083984, "LHS", 1], [0.00167, 195.0, 2.0, 50.0, 0.06805777203816393, 0.0, 0.0015358924865722656, "LHS", 1], [0.003957641640289146, 415.08639917659383, 4, 97.40190793637804, 0.826311971760352, 1.4956939220428467, 0.0021538734436035156, "MTBO", 1], [0.003669615578608733, 438.42981186220743, 4, 93.97917807908662, 0.8007394776306475, 4.4635009765625, 0.001756906509399414, "MTBO", 1], [0.0038951162814164246, 400.8807175559404, 4, 92.12520601336718, 0.7525278112987781, 3.4772298336029053, 0.0017390251159667969, "MTBO", 1], [0.00407871401883316, 451.90876113431955, 4, 95.2285148377906, 0.8396090200299418, 4.237397909164429, 0.0018177032470703125, "MTBO", 1], [0.003926340147533956, 462.2968554641726, 4, 100.67900240693412, 0.8800760745047087, 5.488891124725342, 0.0017781257629394531, "MTBO", 1], [0.0037341992091332573, 510.13596991635984, 4, 98.18811208803885, 0.8714660830926114, 3.0637240409851074, 0.002151966094970703, "MTBO", 1], [0.004087136035930185, 517.6149699613849, 4, 101.44659847165731, 0.9159796364317272, 2.261536121368408, 0.0021822452545166016, "MTBO", 1], [0.003964688441103026, 536.3002381234614, 4, 108.20204429347446, 0.9452228287621098, 4.869693994522095, 0.0018727779388427734, "MTBO", 1], [0.004175, 510.4096267264086, 4, 110.0, 0.9683337552468166, 2.351754903793335, 0.0018661022186279297, "MTBO", 1], [0.004175, 566.6527729097188, 4, 110.0, 0.9855811721964686, 2.9615418910980225, 0.0024399757385253906, "MTBO", 1], [0.004102427671721276, 548.0860271549869, 5, 110.0, 0.9037251310920013, 2.2423250675201416, 0.0018610954284667969, "MTBO", 1], [0.004027724476170394, 434.9504197235024, 5, 110.0, 0.8688382302254034, 3.2526371479034424, 0.002104043960571289, "MTBO", 1], [0.004087220271854285, 510.915840387994, 5, 96.30989638534083, 0.7807504519615314, 2.7654201984405518, 0.0016808509826660156, "MTBO", 1], [0.004175, 600.0, 4, 110.0, 0.9699694255629838, 2.2179200649261475, 0.0022878646850585938, "MTBO", 1], [0.002887211445917225, 600.0, 4, 110.0, 0.9575388053698998, 1.9559807777404785, 0.0025107860565185547, "MTBO", 1], [0.0027367677146220033, 501.4827312017057, 4, 110.0, 0.9383645017508252, 2.125805139541626, 0.0018658638000488281, "MTBO", 1], [0.002209874263245971, 593.6946367915926, 4, 110.0, 0.9300728468495605, 2.7322838306427, 0.0024709701538085938, "MTBO", 1], [0.002574629995386873, 576.1252291419544, 4, 102.67221407168523, 0.9004038449640558, 4.817676067352295, 0.001847982406616211, "MTBO", 1], [0.0016776286009010943, 438.05544772241313, 4, 110.0, 0.8933097231609293, 2.6119320392608643, 0.0021131038665771484, "MTBO", 1]]}, "experiment_params": {"noise_level": 1}, "extras": [{}, {}, {}, {}, {}, {}, {}, {}, {}, {}, {}, {}, {}, {}, {}, {}, {}, {}, {}, {}, {}, {}, {}, {}, {}, {}, {}, {}, {}, {}, {}, {}, {}, {}, {}, {}, {}, {}, {}, {}, {}, {}]}}