{"runner": {"num_initial_experiments": null, "max_iterations": 20, "batch_size": 1, "f_tol": 1e-05, "max_restarts": 0}, "strategy": {"name": "MTBO", "transform": {"transform_domain": [{"type": "ContinuousVariable", "is_objective": false, "maximize": true, "name": "conc_cat", "description": "catalyst concentration", "units": null, "bounds": [0.000835, 0.004175]}, {"type": "ContinuousVariable", "is_objective": false, "maximize": true, "name": "t", "description": "reaction time", "units": null, "bounds": [60.0, 600.0]}, {"type": "CategoricalVariable", "is_objective": false, "maximize": true, "name": "cat_index", "description": "Choice of catalyst", "units": null, "levels": [0, 1, 2, 3, 4, 5, 6, 7], "ds": null}, {"type": "ContinuousVariable", "is_objective": false, "maximize": true, "name": "temperature", "description": "Reactor temperature in degress celsius", "units": null, "bounds": [30.0, 110.0]}, {"type": "ContinuousVariable", "is_objective": true, "maximize": true, "name": "y", "description": "yield (%)", "units": null, "bounds": [0.0, 100.0]}], "name": "Transform", "domain": [{"type": "ContinuousVariable", "is_objective": false, "maximize": true, "name": "conc_cat", "description": "catalyst concentration", "units": null, "bounds": [0.000835, 0.004175]}, {"type": "ContinuousVariable", "is_objective": false, "maximize": true, "name": "t", "description": "reaction time", "units": null, "bounds": [60.0, 600.0]}, {"type": "CategoricalVariable", "is_objective": false, "maximize": true, "name": "cat_index", "description": "Choice of catalyst", "units": null, "levels": [0, 1, 2, 3, 4, 5, 6, 7], "ds": null}, {"type": "ContinuousVariable", "is_objective": false, "maximize": true, "name": "temperature", "description": "Reactor temperature in degress celsius", "units": null, "bounds": [30.0, 110.0]}, {"type": "ContinuousVariable", "is_objective": true, "maximize": true, "name": "y", "description": "yield (%)", "units": null, "bounds": [0.0, 100.0]}], "transform_params": {}}, "strategy_params": {"all_experiments": {"index": [0, 1, 0, 0, 0, 0, 0, 0, 0, 0, 0, 0, 0, 0, 0, 0, 0, 0, 0, 0], "columns": [["conc_cat", "DATA"], ["t", "DATA"], ["cat_index", "DATA"], ["temperature", "DATA"], ["y", "DATA"], ["computation_t", "METADATA"], ["experiment_t", "METADATA"], ["strategy", "METADATA"], ["task", "METADATA"]], "data": [[0.00334, 195.0, 3.0, 90.0, 0.4874600559573748, 0.0, 0.0021469593048095703, "LHS", 1], [0.00167, 465.0, 5.0, 50.0, 0.08043767626694813, 0.0, 0.002482175827026367, "LHS", 1], [0.0033549046263339024, 362.9616858626765, 0, 105.47277911541235, 0.8597389419659034, 1.2532598972320557, 0.002068042755126953, "MTBO", 1], [0.003621077646265565, 438.76517591443877, 0, 103.10235018698364, 0.8940806021091032, 2.769334077835083, 0.002162933349609375, "MTBO", 1], [0.0032360287037502423, 492.04688538269704, 0, 106.17879115657888, 0.9193940376615174, 2.740124225616455, 0.0025339126586914062, "MTBO", 1], [0.003049151004876567, 509.282356889579, 0, 102.38828706241631, 0.9062737958527592, 3.453007936477661, 0.0021810531616210938, "MTBO", 1], [0.0033853119752482105, 571.7582022106402, 0, 106.29477090914739, 0.9124938556941554, 1.3853859901428223, 0.002225160598754883, "MTBO", 1], [0.003460219136652023, 513.8488908476577, 0, 106.61455205022179, 0.9082762159872148, 4.344402074813843, 0.0021839141845703125, "MTBO", 1], [0.0027901507126207887, 558.812235102705, 0, 109.30313647983522, 0.9315233854661182, 4.590017080307007, 0.002368927001953125, "MTBO", 1], [0.003091481886580265, 543.3737360046731, 2, 110.0, 0.9172122480454667, 2.021245241165161, 0.0021638870239257812, "MTBO", 1], [0.0032071323375081288, 600.0, 2, 102.71852534473457, 0.8948700135025486, 3.326495885848999, 0.0021839141845703125, "MTBO", 1], [0.002530923047512293, 600.0, 2, 110.0, 0.9101078097198018, 3.0691208839416504, 0.0021708011627197266, "MTBO", 1], [0.0028878138644294173, 545.4400565261695, 3, 110.0, 0.8754441488893835, 2.077908992767334, 0.0021631717681884766, "MTBO", 1], [0.0031442269036092464, 574.4760776278766, 1, 110.0, 0.9106561075668591, 2.440683126449585, 0.002624988555908203, "MTBO", 1], [0.003677323580947579, 467.5237102041325, 1, 110.0, 0.9105285754962109, 2.667243003845215, 0.0021958351135253906, "MTBO", 1], [0.0029111171480063146, 474.802426972375, 1, 110.0, 0.8874001236874753, 2.418692111968994, 0.002480745315551758, "MTBO", 1], [0.0027247015784690543, 600.0, 0, 110.0, 0.9145624078308248, 2.046211004257202, 0.0022935867309570312, "MTBO", 1], [0.003743014583976455, 556.7305744386412, 1, 104.45134284055308, 0.9187358918479245, 2.012864112854004, 0.0021886825561523438, "MTBO", 1], [0.002771563415238247, 516.2676002652031, 0, 110.0, 0.9094580456381063, 2.205862045288086, 0.00261688232421875, "MTBO", 1], [0.003192438085747565, 548.7177902788271, 4, 110.0, 0.8857909367269222, 2.7740979194641113, 0.002512216567993164, "MTBO", 1]]}, "categorical_method": "one-hot", "task": 1}}, "experiment": {"domain": [{"type": "ContinuousVariable", "is_objective": false, "maximize": true, "name": "conc_cat", "description": "catalyst concentration", "units": null, "bounds": [0.000835, 0.004175]}, {"type": "ContinuousVariable", "is_objective": false, "maximize": true, "name": "t", "description": "reaction time", "units": null, "bounds": [60.0, 600.0]}, {"type": "CategoricalVariable", "is_objective": false, "maximize": true, "name": "cat_index", "description": "Choice of catalyst", "units": null, "levels": [0, 1, 2, 3, 4, 5, 6, 7], "ds": null}, {"type": "ContinuousVariable", "is_objective": false, "maximize": true, "name": "temperature", "description": "Reactor temperature in degress celsius", "units": null, "bounds": [30.0, 110.0]}, {"type": "ContinuousVariable", "is_objective": true, "maximize": true, "name": "y", "description": "yield (%)", "units": null, "bounds": [0.0, 100.0]}], "name": "MIT_case3", "data": {"index": [0, 1, 2, 3, 4, 5, 6, 7, 8, 9, 10, 11, 12, 13, 14, 15, 16, 17, 18, 19, 20], "columns": [["conc_cat", "DATA"], ["t", "DATA"], ["cat_index", "DATA"], ["temperature", "DATA"], ["y", "DATA"], ["computation_t", "METADATA"], ["experiment_t", "METADATA"], ["strategy", "METADATA"], ["task", "METADATA"]], "data": [[0.00334, 195.0, 3.0, 90.0, 0.4874600559573748, 0.0, 0.0021469593048095703, "LHS", 1], [0.00167, 465.0, 5.0, 50.0, 0.08043767626694813, 0.0, 0.002482175827026367, "LHS", 1], [0.0033549046263339024, 362.9616858626765, 0, 105.47277911541235, 0.8597389419659034, 1.2532598972320557, 0.002068042755126953, "MTBO", 1], [0.003621077646265565, 438.76517591443877, 0, 103.10235018698364, 0.8940806021091032, 2.769334077835083, 0.002162933349609375, "MTBO", 1], [0.0032360287037502423, 492.04688538269704, 0, 106.17879115657888, 0.9193940376615174, 2.740124225616455, 0.0025339126586914062, "MTBO", 1], [0.003049151004876567, 509.282356889579, 0, 102.38828706241631, 0.9062737958527592, 3.453007936477661, 0.0021810531616210938, "MTBO", 1], [0.0033853119752482105, 571.7582022106402, 0, 106.29477090914739, 0.9124938556941554, 1.3853859901428223, 0.002225160598754883, "MTBO", 1], [0.003460219136652023, 513.8488908476577, 0, 106.61455205022179, 0.9082762159872148, 4.344402074813843, 0.0021839141845703125, "MTBO", 1], [0.0027901507126207887, 558.812235102705, 0, 109.30313647983522, 0.9315233854661182, 4.590017080307007, 0.002368927001953125, "MTBO", 1], [0.003091481886580265, 543.3737360046731, 2, 110.0, 0.9172122480454667, 2.021245241165161, 0.0021638870239257812, "MTBO", 1], [0.0032071323375081288, 600.0, 2, 102.71852534473457, 0.8948700135025486, 3.326495885848999, 0.0021839141845703125, "MTBO", 1], [0.002530923047512293, 600.0, 2, 110.0, 0.9101078097198018, 3.0691208839416504, 0.0021708011627197266, "MTBO", 1], [0.0028878138644294173, 545.4400565261695, 3, 110.0, 0.8754441488893835, 2.077908992767334, 0.0021631717681884766, "MTBO", 1], [0.0031442269036092464, 574.4760776278766, 1, 110.0, 0.9106561075668591, 2.440683126449585, 0.002624988555908203, "MTBO", 1], [0.003677323580947579, 467.5237102041325, 1, 110.0, 0.9105285754962109, 2.667243003845215, 0.0021958351135253906, "MTBO", 1], [0.0029111171480063146, 474.802426972375, 1, 110.0, 0.8874001236874753, 2.418692111968994, 0.002480745315551758, "MTBO", 1], [0.0027247015784690543, 600.0, 0, 110.0, 0.9145624078308248, 2.046211004257202, 0.0022935867309570312, "MTBO", 1], [0.003743014583976455, 556.7305744386412, 1, 104.45134284055308, 0.9187358918479245, 2.012864112854004, 0.0021886825561523438, "MTBO", 1], [0.002771563415238247, 516.2676002652031, 0, 110.0, 0.9094580456381063, 2.205862045288086, 0.00261688232421875, "MTBO", 1], [0.003192438085747565, 548.7177902788271, 4, 110.0, 0.8857909367269222, 2.7740979194641113, 0.002512216567993164, "MTBO", 1], [0.004000731007664072, 580.8209448795817, 1, 110.0, 0.9275571676427493, 2.5370728969573975, 0.00263214111328125, "MTBO", 1]]}, "experiment_params": {"noise_level": 1}, "extras": [{}, {}, {}, {}, {}, {}, {}, {}, {}, {}, {}, {}, {}, {}, {}, {}, {}, {}, {}, {}, {}, {}, {}, {}, {}, {}, {}, {}, {}, {}, {}, {}, {}, {}, {}, {}, {}, {}, {}, {}, {}, {}]}}